{
    "ok": "ઠીક",
    "missing_fields": "માહિતી અધૂરી છે",
    "email_exists": "ઈમેલ પહેલેથી જ નોંધાયેલ છે",
    "signup_error": "સાઇનઅપ ભૂલ",
    "missing_credentials": "જરૂરી માહિતી નથી",
    "invalid_credentials": "ઈમેલ અથવા પાસવર્ડ ખોટો છે",
    "login_error": "લૉગિન ભૂલ",
    "missing_or_malformed_token": "ટોકન ગાયબ છે અથવા ખોટું છે",
    "invalid_token": "અમાન્ય ટોકન",
    "profile_fetch_failed": "પ્રોફાઇલ મેળવવામાં નિષ્ફળ",
    "unsupported_language": "ભાષાનું સમર્થન નથી",
    "profile_update_failed": "પ્રોફાઇલ અપડેટ નિષ્ફળ",
    "family_create_failed": "પરિવાર બનાવવામાં નિષ્ફળ",
    "family_not_found": "પરિવાર મળ્યો નથી",
    "family_join_failed": "પરિવારમાં જોડાવામાં નિષ્ફળ",
    "not_family_member": "પ્રતિબંધિત: તમે આ પરિવારના સભ્ય નથી.",
    "family_members_failed": "પરિવારના સભ્યો મેળવવામાં નિષ્ફળ",
    "not_in_family": "તમે કોઈ પરિવારમાં નથી.",
    "owner_must_transfer": "બહાર જતા પહેલાં નવા માલીકને નિયુક્ત કરો.",
    "left_family": "તમે પરિવાર છોડ્યો છે.",
    "family_leave_failed": "પરિવાર છોડવામાં નિષ્ફળ",
    "welcome_user": "સ્વાગત છે, {{name}}!"
  }
  